MANIFEST.in
setup.py
formulas/__init__.py
formulas/nginx/__init__.py
formulas/nginx/files/proxy.nginx
formulas/nginx/files/static_website.nginx
formulas/nodejs/__init__.py
formulas/nodejs/files/pubkey.gpg
pyinfra_formulas.egg-info/PKG-INFO
pyinfra_formulas.egg-info/SOURCES.txt
pyinfra_formulas.egg-info/dependency_links.txt
pyinfra_formulas.egg-info/requires.txt
pyinfra_formulas.egg-info/top_level.txt